agenthotspot_mcp/__init__.py
agenthotspot_mcp/__main__.py
agenthotspot_mcp/server.py
agenthotspot_mcp-1.0.2.dist-info/METADATA
agenthotspot_mcp-1.0.2.dist-info/WHEEL
agenthotspot_mcp-1.0.2.dist-info/licenses/LICENSE
agenthotspot_mcp-1.0.2.dist-info/RECORD
