Metadata-Version: 2.4
Name: agenthotspot-mcp
Version: 1.0.2
Summary: MCP server to search and discover connectors from AgentHotspot.com marketplace
Project-URL: Homepage, https://agenthotspot.com
Project-URL: Documentation, https://github.com/AgentHotspot/agenthotspot-mcp#readme
Project-URL: Repository, https://github.com/AgentHotspot/agenthotspot-mcp
Project-URL: Issues, https://github.com/AgentHotspot/agenthotspot-mcp/issues
Author-email: AgentHotspot <support@agenthotspot.com>
License-Expression: MIT
License-File: LICENSE
Keywords: agenthotspot,ai-agents,claude,connectors,llm,marketplace,mcp,model-context-protocol,openai
Classifier: Development Status :: 4 - Beta
Classifier: Intended Audience :: Developers
Classifier: License :: OSI Approved :: MIT License
Classifier: Operating System :: OS Independent
Classifier: Programming Language :: Python :: 3
Classifier: Programming Language :: Python :: 3.10
Classifier: Programming Language :: Python :: 3.11
Classifier: Programming Language :: Python :: 3.12
Classifier: Programming Language :: Python :: 3.13
Classifier: Topic :: Scientific/Engineering :: Artificial Intelligence
Classifier: Topic :: Software Development :: Libraries :: Python Modules
Requires-Python: >=3.10
Requires-Dist: fastmcp>=0.1.0
Requires-Dist: httpx>=0.24.0
Provides-Extra: dev
Requires-Dist: mypy>=1.0.0; extra == 'dev'
Requires-Dist: pytest-asyncio>=0.21.0; extra == 'dev'
Requires-Dist: pytest>=7.0.0; extra == 'dev'
Requires-Dist: ruff>=0.1.0; extra == 'dev'
Provides-Extra: langchain
Requires-Dist: langchain-mcp-adapters>=0.1.0; extra == 'langchain'
